README.md
setup.py
taxi_multi/__init__.py
taxi_multi/backend.py
taxi_multi.egg-info/PKG-INFO
taxi_multi.egg-info/SOURCES.txt
taxi_multi.egg-info/dependency_links.txt
taxi_multi.egg-info/entry_points.txt
taxi_multi.egg-info/requires.txt
taxi_multi.egg-info/top_level.txt